weight_of_evidence/__init__.py
weight_of_evidence/tree_binner.py
weight_of_evidence-0.1.0.dist-info/METADATA
weight_of_evidence-0.1.0.dist-info/WHEEL
weight_of_evidence-0.1.0.dist-info/RECORD
